rssmcp/__init__.py
rssmcp/config.yaml
rssmcp/feeds.opml
rssmcp/feeds_mod.opml
rssmcp/server.py
rssmcp/utils.py
rssmcp-0.1.1.dist-info/METADATA
rssmcp-0.1.1.dist-info/WHEEL
rssmcp-0.1.1.dist-info/entry_points.txt
rssmcp-0.1.1.dist-info/licenses/LICENSE
rssmcp-0.1.1.dist-info/RECORD
