Metadata-Version: 2.4
Name: rssmcp
Version: 0.1.1
Summary: Simple RSS MCP Server
Author-email: Lunran <feitcounter@gmail.com>
License-File: LICENSE
Requires-Python: >=3.10.16
Requires-Dist: feedparser>=6.0.11
Requires-Dist: mcp>=1.6.0
Requires-Dist: pyyaml>=6.0.2
Requires-Dist: types-pyyaml>=6.0.12.20250402
